{
   "metadata" : {
      "creator" : "Rapid API C++",
      "inputNames" : [
         "inputs-1",
         "inputs-2",
         "inputs-3",
         "inputs-4",
         "inputs-5",
         "inputs-6"
      ],
      "numInputs" : 6,
      "numOutputs" : 1,
      "version" : "v0.1.1"
   },
   "modelSet" : [
      {
         "examples" : [
            {
               "class" : 1,
               "features" : [
                  -0.13796193897724152,
                  1.3971192836761475,
                  1.2919282913208008,
                  -0.19630783796310425,
                  1.5131850242614746,
                  1.4794658422470093
               ]
            },
            {
               "class" : 1,
               "features" : [
                  -0.1389358788728714,
                  1.3961019515991211,
                  1.2907164096832275,
                  -0.19641241431236267,
                  1.5130472183227539,
                  1.4782356023788452
               ]
            },
            {
               "class" : 1,
               "features" : [
                  -0.13797701895236969,
                  1.3978663682937622,
                  1.2886054515838623,
                  -0.1964479386806488,
                  1.5134490728378296,
                  1.4769318103790283
               ]
            },
            {
               "class" : 1,
               "features" : [
                  -0.13773028552532196,
                  1.3982062339782715,
                  1.2882055044174194,
                  -0.19641922414302826,
                  1.5135066509246826,
                  1.4767073392868042
               ]
            },
            {
               "class" : 1,
               "features" : [
                  -0.13773235678672791,
                  1.3982034921646118,
                  1.2882084846496582,
                  -0.19641716778278351,
                  1.5135077238082886,
                  1.4767013788223267
               ]
            },
            {
               "class" : 1,
               "features" : [
                  -0.13770130276679993,
                  1.3981708288192749,
                  1.2882390022277832,
                  -0.1963975578546524,
                  1.5134884119033813,
                  1.4767167568206787
               ]
            },
            {
               "class" : 1,
               "features" : [
                  -0.13770025968551636,
                  1.3981697559356689,
                  1.2882400751113892,
                  -0.19639690220355988,
                  1.513487696647644,
                  1.4767172336578369
               ]
            },
            {
               "class" : 1,
               "features" : [
                  -0.13770000636577606,
                  1.3981695175170898,
                  1.2882403135299683,
                  -0.19639673829078674,
                  1.5134875774383545,
                  1.4767173528671265
               ]
            },
            {
               "class" : 1,
               "features" : [
                  -0.13770000636577606,
                  1.3981695175170898,
                  1.2882403135299683,
                  -0.19639673829078674,
                  1.5134875774383545,
                  1.4767173528671265
               ]
            },
            {
               "class" : 1,
               "features" : [
                  -0.13770250976085663,
                  1.3981692790985107,
                  1.2882425785064697,
                  -0.19639718532562256,
                  1.5134875774383545,
                  1.4767200946807861
               ]
            },
            {
               "class" : 1,
               "features" : [
                  -0.13770249485969543,
                  1.3981692790985107,
                  1.2882425785064697,
                  -0.19639720022678375,
                  1.5134875774383545,
                  1.4767202138900757
               ]
            },
            {
               "class" : 1,
               "features" : [
                  -0.13770250976085663,
                  1.3981692790985107,
                  1.2882425785064697,
                  -0.19639720022678375,
                  1.5134875774383545,
                  1.4767202138900757
               ]
            },
            {
               "class" : 1,
               "features" : [
                  -0.13770250976085663,
                  1.3981692790985107,
                  1.2882425785064697,
                  -0.19639720022678375,
                  1.5134875774383545,
                  1.4767202138900757
               ]
            },
            {
               "class" : 1,
               "features" : [
                  -0.13770250976085663,
                  1.3981692790985107,
                  1.2882425785064697,
                  -0.19639720022678375,
                  1.5134875774383545,
                  1.4767202138900757
               ]
            },
            {
               "class" : 1,
               "features" : [
                  -0.13770250976085663,
                  1.3981692790985107,
                  1.2882425785064697,
                  -0.19639720022678375,
                  1.5134875774383545,
                  1.4767202138900757
               ]
            },
            {
               "class" : 1,
               "features" : [
                  -0.13770250976085663,
                  1.3981692790985107,
                  1.2882425785064697,
                  -0.19639720022678375,
                  1.5134875774383545,
                  1.4767202138900757
               ]
            },
            {
               "class" : 1,
               "features" : [
                  -0.13770250976085663,
                  1.3981692790985107,
                  1.2882425785064697,
                  -0.19639720022678375,
                  1.5134875774383545,
                  1.4767202138900757
               ]
            },
            {
               "class" : 1,
               "features" : [
                  -0.13770250976085663,
                  1.3981692790985107,
                  1.2882425785064697,
                  -0.19639720022678375,
                  1.5134875774383545,
                  1.4767202138900757
               ]
            },
            {
               "class" : 1,
               "features" : [
                  -0.13770250976085663,
                  1.3981692790985107,
                  1.2882425785064697,
                  -0.19639720022678375,
                  1.5134875774383545,
                  1.4767202138900757
               ]
            },
            {
               "class" : 1,
               "features" : [
                  -0.13770250976085663,
                  1.3981692790985107,
                  1.2882425785064697,
                  -0.19639720022678375,
                  1.5134875774383545,
                  1.4767202138900757
               ]
            },
            {
               "class" : 1,
               "features" : [
                  -0.13770250976085663,
                  1.3981692790985107,
                  1.2882425785064697,
                  -0.19639720022678375,
                  1.5134875774383545,
                  1.4767202138900757
               ]
            },
            {
               "class" : 1,
               "features" : [
                  -0.13770250976085663,
                  1.3981692790985107,
                  1.2882425785064697,
                  -0.19639720022678375,
                  1.5134875774383545,
                  1.4767202138900757
               ]
            },
            {
               "class" : 1,
               "features" : [
                  -0.13770250976085663,
                  1.3981692790985107,
                  1.2882425785064697,
                  -0.19639720022678375,
                  1.5134875774383545,
                  1.4767202138900757
               ]
            },
            {
               "class" : 1,
               "features" : [
                  -0.13770250976085663,
                  1.3981692790985107,
                  1.2882425785064697,
                  -0.19639720022678375,
                  1.5134875774383545,
                  1.4767202138900757
               ]
            },
            {
               "class" : 1,
               "features" : [
                  -0.13749654591083527,
                  1.3978173732757568,
                  1.2886825799942017,
                  -0.19613556563854218,
                  1.5133740901947021,
                  1.4769879579544067
               ]
            },
            {
               "class" : 1,
               "features" : [
                  -0.13747349381446838,
                  1.3977224826812744,
                  1.288818359375,
                  -0.19608035683631897,
                  1.5133434534072876,
                  1.4770857095718384
               ]
            },
            {
               "class" : 1,
               "features" : [
                  -0.1374795138835907,
                  1.3977173566818237,
                  1.2888295650482178,
                  -0.19608078896999359,
                  1.5133419036865234,
                  1.4770964384078979
               ]
            },
            {
               "class" : 1,
               "features" : [
                  -0.13748112320899963,
                  1.3977159261703491,
                  1.2888326644897461,
                  -0.19608096778392792,
                  1.5133416652679443,
                  1.4770994186401367
               ]
            },
            {
               "class" : 1,
               "features" : [
                  -0.13720428943634033,
                  1.397627592086792,
                  1.2888343334197998,
                  -0.19586780667304993,
                  1.5131665468215942,
                  1.4771513938903809
               ]
            },
            {
               "class" : 1,
               "features" : [
                  -0.13711895048618317,
                  1.3974707126617432,
                  1.2889139652252197,
                  -0.19581404328346252,
                  1.5130746364593506,
                  1.4771875143051147
               ]
            },
            {
               "class" : 1,
               "features" : [
                  -0.13706479966640472,
                  1.3974659442901611,
                  1.2887402772903442,
                  -0.19585485756397247,
                  1.5130907297134399,
                  1.4769703149795532
               ]
            },
            {
               "class" : 1,
               "features" : [
                  -0.1370600163936615,
                  1.3974744081497192,
                  1.2886757850646973,
                  -0.19586822390556335,
                  1.5130957365036011,
                  1.476904034614563
               ]
            },
            {
               "class" : 1,
               "features" : [
                  -0.1370798647403717,
                  1.3974649906158447,
                  1.2886918783187866,
                  -0.19587866961956024,
                  1.5130972862243652,
                  1.4769138097763062
               ]
            },
            {
               "class" : 1,
               "features" : [
                  -0.13704074919223785,
                  1.3974981307983398,
                  1.2885106801986694,
                  -0.19591444730758667,
                  1.5131046772003174,
                  1.4767100811004639
               ]
            },
            {
               "class" : 1,
               "features" : [
                  -0.13703376054763794,
                  1.3975036144256592,
                  1.2884637117385864,
                  -0.19592621922492981,
                  1.5131069421768188,
                  1.4766552448272705
               ]
            },
            {
               "class" : 1,
               "features" : [
                  -0.13704128563404083,
                  1.3974796533584595,
                  1.288490891456604,
                  -0.19593021273612976,
                  1.5131080150604248,
                  1.4766671657562256
               ]
            },
            {
               "class" : 1,
               "features" : [
                  -0.1382891982793808,
                  1.3963440656661987,
                  1.2897095680236816,
                  -0.19621437788009644,
                  1.5128058195114136,
                  1.4777592420578003
               ]
            },
            {
               "class" : 2,
               "features" : [
                  -0.049033842980861664,
                  1.6340698003768921,
                  0.93087112903594971,
                  -0.1304326057434082,
                  1.6715359687805176,
                  1.1372566223144531
               ]
            },
            {
               "class" : 2,
               "features" : [
                  -0.017985716462135315,
                  1.5965325832366943,
                  0.95357835292816162,
                  -0.1303727924823761,
                  1.6483592987060547,
                  1.1417908668518066
               ]
            },
            {
               "class" : 2,
               "features" : [
                  -0.044080756604671478,
                  1.6262962818145752,
                  0.93493658304214478,
                  -0.13124942779541016,
                  1.6602493524551392,
                  1.1389058828353882
               ]
            },
            {
               "class" : 2,
               "features" : [
                  -0.047878570854663849,
                  1.6311615705490112,
                  0.92905682325363159,
                  -0.12742772698402405,
                  1.6636748313903809,
                  1.1354365348815918
               ]
            },
            {
               "class" : 2,
               "features" : [
                  -0.0489012710750103,
                  1.6235902309417725,
                  0.93101853132247925,
                  -0.12745113670825958,
                  1.6587852239608765,
                  1.137059211730957
               ]
            },
            {
               "class" : 2,
               "features" : [
                  -0.044718217104673386,
                  1.6314300298690796,
                  0.93167811632156372,
                  -0.12621437013149261,
                  1.663105845451355,
                  1.1360646486282349
               ]
            },
            {
               "class" : 2,
               "features" : [
                  -0.037663396447896957,
                  1.6338481903076172,
                  0.93271380662918091,
                  -0.12636049091815948,
                  1.6611626148223877,
                  1.1354632377624512
               ]
            },
            {
               "class" : 2,
               "features" : [
                  -0.021564602851867676,
                  1.6029460430145264,
                  0.95716249942779541,
                  -0.1257779449224472,
                  1.647411584854126,
                  1.1483381986618042
               ]
            },
            {
               "class" : 2,
               "features" : [
                  -0.045356728136539459,
                  1.6375255584716797,
                  0.9355197548866272,
                  -0.1301235556602478,
                  1.6538668870925903,
                  1.1435962915420532
               ]
            },
            {
               "class" : 2,
               "features" : [
                  -0.046623308211565018,
                  1.6384425163269043,
                  0.93520569801330566,
                  -0.13208205997943878,
                  1.6555862426757812,
                  1.1427816152572632
               ]
            },
            {
               "class" : 2,
               "features" : [
                  -0.046825725585222244,
                  1.6390070915222168,
                  0.93493306636810303,
                  -0.13254144787788391,
                  1.6559590101242065,
                  1.1426032781600952
               ]
            },
            {
               "class" : 2,
               "features" : [
                  -0.046824697405099869,
                  1.6390049457550049,
                  0.93493425846099854,
                  -0.13255612552165985,
                  1.6559652090072632,
                  1.1426002979278564
               ]
            },
            {
               "class" : 2,
               "features" : [
                  -0.046825498342514038,
                  1.6390068531036377,
                  0.93493330478668213,
                  -0.13255906105041504,
                  1.6559664011001587,
                  1.1425997018814087
               ]
            },
            {
               "class" : 2,
               "features" : [
                  -0.050215840339660645,
                  1.6341055631637573,
                  0.93335503339767456,
                  -0.12980030477046967,
                  1.6603057384490967,
                  1.142525315284729
               ]
            },
            {
               "class" : 2,
               "features" : [
                  -0.050325773656368256,
                  1.6339422464370728,
                  0.93330293893814087,
                  -0.12970641255378723,
                  1.6604501008987427,
                  1.1425226926803589
               ]
            },
            {
               "class" : 2,
               "features" : [
                  -0.050352156162261963,
                  1.6339030265808105,
                  0.93329042196273804,
                  -0.12968388199806213,
                  1.660484790802002,
                  1.1425219774246216
               ]
            },
            {
               "class" : 2,
               "features" : [
                  -0.050277791917324066,
                  1.6339453458786011,
                  0.93324089050292969,
                  -0.12964117527008057,
                  1.6605193614959717,
                  1.1424659490585327
               ]
            },
            {
               "class" : 2,
               "features" : [
                  -0.05016123503446579,
                  1.6339532136917114,
                  0.93320757150650024,
                  -0.12957543134689331,
                  1.6605231761932373,
                  1.1424156427383423
               ]
            },
            {
               "class" : 2,
               "features" : [
                  -0.046075623482465744,
                  1.6337995529174805,
                  0.93152683973312378,
                  -0.13053537905216217,
                  1.6630382537841797,
                  1.1383622884750366
               ]
            },
            {
               "class" : 2,
               "features" : [
                  -0.045016691088676453,
                  1.632251501083374,
                  0.93506455421447754,
                  -0.12890425324440002,
                  1.6566997766494751,
                  1.1395022869110107
               ]
            },
            {
               "class" : 2,
               "features" : [
                  -0.045230686664581299,
                  1.6323404312133789,
                  0.93451029062271118,
                  -0.12870132923126221,
                  1.6557176113128662,
                  1.1395531892776489
               ]
            },
            {
               "class" : 2,
               "features" : [
                  -0.059038955718278885,
                  1.5864410400390625,
                  1.0101813077926636,
                  -0.16261276602745056,
                  1.6390194892883301,
                  1.183896541595459
               ]
            },
            {
               "class" : 2,
               "features" : [
                  -0.052236039191484451,
                  1.6476916074752808,
                  0.99285596609115601,
                  -0.16738313436508179,
                  1.6474467515945435,
                  1.1810061931610107
               ]
            },
            {
               "class" : 2,
               "features" : [
                  -0.046784639358520508,
                  1.6460074186325073,
                  0.99298113584518433,
                  -0.16396297514438629,
                  1.64509117603302,
                  1.181740403175354
               ]
            },
            {
               "class" : 2,
               "features" : [
                  -0.060071520507335663,
                  1.645399808883667,
                  0.97027349472045898,
                  -0.14431676268577576,
                  1.6503641605377197,
                  1.1751083135604858
               ]
            },
            {
               "class" : 2,
               "features" : [
                  -0.061495434492826462,
                  1.6383533477783203,
                  0.93669295310974121,
                  -0.13509474694728851,
                  1.6546746492385864,
                  1.1466546058654785
               ]
            },
            {
               "class" : 2,
               "features" : [
                  -0.058493424206972122,
                  1.6377222537994385,
                  0.93338334560394287,
                  -0.13161949813365936,
                  1.6547608375549316,
                  1.1424016952514648
               ]
            },
            {
               "class" : 2,
               "features" : [
                  -0.062165454030036926,
                  1.6375420093536377,
                  0.93362522125244141,
                  -0.13177144527435303,
                  1.6571033000946045,
                  1.1439594030380249
               ]
            },
            {
               "class" : 2,
               "features" : [
                  -0.063282474875450134,
                  1.6433595418930054,
                  0.95204389095306396,
                  -0.13846999406814575,
                  1.6562861204147339,
                  1.1595865488052368
               ]
            },
            {
               "class" : 2,
               "features" : [
                  -0.070846781134605408,
                  1.6419379711151123,
                  0.9455147385597229,
                  -0.13182321190834045,
                  1.6705948114395142,
                  1.1560148000717163
               ]
            },
            {
               "class" : 2,
               "features" : [
                  -0.057850606739521027,
                  1.6810423135757446,
                  0.94540542364120483,
                  -0.11674603819847107,
                  1.7227363586425781,
                  1.1558866500854492
               ]
            },
            {
               "class" : 2,
               "features" : [
                  -0.051840614527463913,
                  1.710443377494812,
                  0.95223021507263184,
                  -0.12996210157871246,
                  1.7475783824920654,
                  1.1577891111373901
               ]
            },
            {
               "class" : 2,
               "features" : [
                  -0.058906327933073044,
                  1.6952358484268188,
                  0.95017331838607788,
                  -0.11749706417322159,
                  1.7478585243225098,
                  1.160430908203125
               ]
            },
            {
               "class" : 2,
               "features" : [
                  -0.050642795860767365,
                  1.7112902402877808,
                  0.95459824800491333,
                  -0.12672792375087738,
                  1.7555832862854004,
                  1.1594569683074951
               ]
            },
            {
               "class" : 2,
               "features" : [
                  -0.039365652948617935,
                  1.7329565286636353,
                  0.96319258213043213,
                  -0.13760961592197418,
                  1.7666211128234863,
                  1.159915566444397
               ]
            },
            {
               "class" : 2,
               "features" : [
                  -0.037583295255899429,
                  1.7365231513977051,
                  0.96474575996398926,
                  -0.1394941508769989,
                  1.7684210538864136,
                  1.160076379776001
               ]
            },
            {
               "class" : 2,
               "features" : [
                  -0.037148308008909225,
                  1.7373783588409424,
                  0.96511965990066528,
                  -0.13994258642196655,
                  1.768851637840271,
                  1.1601142883300781
               ]
            },
            {
               "class" : 2,
               "features" : [
                  -0.037133261561393738,
                  1.7374067306518555,
                  0.96513217687606812,
                  -0.1399572342634201,
                  1.7688658237457275,
                  1.1601154804229736
               ]
            },
            {
               "class" : 2,
               "features" : [
                  -0.03712964802980423,
                  1.7374136447906494,
                  0.96513521671295166,
                  -0.13996075093746185,
                  1.7688692808151245,
                  1.1601157188415527
               ]
            },
            {
               "class" : 2,
               "features" : [
                  -0.037129528820514679,
                  1.7374138832092285,
                  0.96513533592224121,
                  -0.1399608701467514,
                  1.7688694000244141,
                  1.1601157188415527
               ]
            },
            {
               "class" : 2,
               "features" : [
                  -0.037129499018192291,
                  1.7374138832092285,
                  0.96513533592224121,
                  -0.13996089994907379,
                  1.7688694000244141,
                  1.1601157188415527
               ]
            },
            {
               "class" : 2,
               "features" : [
                  -0.037129499018192291,
                  1.7374138832092285,
                  0.96513533592224121,
                  -0.13996089994907379,
                  1.7688694000244141,
                  1.1601157188415527
               ]
            },
            {
               "class" : 2,
               "features" : [
                  -0.035814177244901657,
                  1.7374755144119263,
                  0.96506506204605103,
                  -0.13928873836994171,
                  1.7689199447631836,
                  1.1597115993499756
               ]
            },
            {
               "class" : 2,
               "features" : [
                  -0.035763528198003769,
                  1.737479567527771,
                  0.96506309509277344,
                  -0.13926313817501068,
                  1.7689225673675537,
                  1.1596968173980713
               ]
            }
         ],
         "inputNames" : [
            "inputs-1",
            "inputs-2",
            "inputs-3",
            "inputs-4",
            "inputs-5",
            "inputs-6"
         ],
         "k" : 1,
         "modelType" : "kNN Classificiation",
         "numInputs" : 6,
         "whichInputs" : [ 0, 1, 2, 3, 4, 5 ]
      }
   ]
}
